itk_rtk_cuda116.libs/libtbb-3c88584c.so.12.9
itk/rtkFourDToProjectionStackImageFilterPython.py
itk/rtkprojectors_group.py
itk/rtkSARTConeBeamReconstructionFilterPython.py
itk/rtkProjectGeometricPhantomImageFilterPython.py
itk/rtkMaskCollimationImageFilterPython.py
itk/itkImageRegionRTKPython.py
itk/rtkOSEMConeBeamReconstructionFilterPython.py
itk/rtkDrawEllipsoidImageFilterPython.py
itk/rtkFDKWeightProjectionFilterPython.py
itk/rtkFDKWarpBackProjectionImageFilterPython.py
itk/rtkMechlemOneStepSpectralReconstructionFilterPython.py
itk/rtkBioscanGeometryReaderPython.py
itk/rtkDrawSheppLoganFilterPython.py
itk/rtkFDKVarianceReconstructionFilterPython.py
itk/rtkFourDConjugateGradientConeBeamReconstructionFilterPython.py
itk/itkContinuousIndexRTKPython.py
itk/rtkLastDimensionL0GradientDenoisingImageFilterPython.py
itk/itkImageRTKPython.py
itk/rtkGeometricPhantomFileReaderPython.py
itk/rtkSimplexSpectralProjectionsDecompositionImageFilterPython.py
itk/rtkFourDROOSTERConeBeamReconstructionFilterPython.py
itk/rtkPolynomialGainCorrectionImageFilterPython.py
itk/rtkCudaSplatImageFilterPython.py
itk/rtkHisImageIOPython.py
itk/rtkElektaSynergyRawLookupTableImageFilterPython.py
itk/rtkFFTVarianceRampImageFilterPython.py
itk/rtkDrawQuadricImageFilterPython.py
itk/itkCudaInPlaceImageFilterRTKPython.py
itk/itkVariableLengthVectorRTKPython.py
itk/rtkThreeDCircularProjectionGeometryXMLFileReaderPython.py
itk/itkVectorImageRTKPython.py
itk/rtkTotalVariationImageFilterPython.py
itk/rtkElektaXVI5GeometryXMLFileReaderPython.py
itk/rtkDCMImagXImageIOPython.py
itk/rtkCudaIterativeFDKConeBeamReconstructionFilterPython.py
itk/rtkJosephBackAttenuatedProjectionImageFilterPython.py
itk/itkPointRTKPython.py
itk/rtkJosephForwardProjectionImageFilterPython.py
itk/rtkIntersectionOfConvexShapesPython.py
itk/rtkFDKBackProjectionImageFilterPython.py
itk/rtkGlobalResourceProbePython.py
itk/rtkXimImageIOPython.py
itk/rtkForwardProjectionImageFilterPython.py
itk_rtk_cuda116-2.7.0.post1.dist-info/WHEEL
itk_rtk_cuda116-2.7.0.post1.dist-info/RECORD
itk_rtk_cuda116-2.7.0.post1.dist-info/entry_points.txt
itk_rtk_cuda116-2.7.0.post1.dist-info/METADATA
itk_rtk_cuda116-2.7.0.post1.dist-info/licenses/LICENSE.TXT
